{"chunk_definitions":[{"row":19,"row_count":1,"visible":true,"expansion_state":0,"options":{"engine":"r","label":"unnamed-chunk-1"},"document_id":null,"chunk_id":"ci83uby5lctcj","chunk_label":"unnamed-chunk-1"},{"row":25,"row_count":1,"visible":true,"expansion_state":0,"options":{"engine":"sql","connection":"mydb","label":"unnamed-chunk-2"},"document_id":null,"chunk_id":"cg8rarry6ei7t","chunk_label":"unnamed-chunk-2"},{"row":30,"row_count":1,"visible":true,"expansion_state":0,"options":{"engine":"sql","connection":"mydb","label":"unnamed-chunk-1"},"document_id":null,"chunk_id":"cnia0x92r7kl4","chunk_label":"unnamed-chunk-3"}],"doc_write_time":1670437489}